{
	"cerberusorg": { 
	"label": "cerberusorg",
	"msp": "CerberusOrgMSP",
	"name": "CerberusOrg",
	"channels": [
		{
			"channel": "personaccountsch"
		},
		{
			"channel": "institutionaccountsch"
		},
		{
			"channel": "integrationaccountsch"
		}
	]
},
{
	"whitebox": {
	"label": "whitebox",
	"msp": "WhiteBoxMSP",
        "name": "WhiteBox",
        "channels": [
		{
			"channel": "personaccountsch"
		},
		{
			"channel": "institutionaccountsch"
		},
		{
			"channel": "integrationaccountsch"
		}
	]
}
